langchain_envector/__init__.py
langchain_envector/client.py
langchain_envector/config.py
langchain_envector/py.typed
langchain_envector/retriever.py
langchain_envector/types.py
langchain_envector/vectorstore.py
langchain_envector-0.1.3.dist-info/METADATA
langchain_envector-0.1.3.dist-info/WHEEL
langchain_envector-0.1.3.dist-info/top_level.txt
langchain_envector-0.1.3.dist-info/RECORD
