Metadata-Version: 2.4
Name: langchain-envector
Version: 0.1.3
Summary: LangChain VectorStore integration for Envector
Author: Envector Contributors
License: MIT
Project-URL: Homepage, https://example.com/
Project-URL: Repository, https://example.com/repo
Keywords: langchain,vectorstore,homomorphic-encryption,ckks,encrypted-search,envector,pyenvector
Classifier: Programming Language :: Python :: 3
Classifier: Programming Language :: Python :: 3.9
Classifier: Programming Language :: Python :: 3.10
Classifier: Programming Language :: Python :: 3.11
Classifier: Programming Language :: Python :: 3.12
Classifier: Programming Language :: Python :: 3.13
Classifier: Operating System :: OS Independent
Classifier: Intended Audience :: Developers
Classifier: Topic :: Scientific/Engineering :: Artificial Intelligence
Requires-Python: <3.14,>=3.9
Requires-Dist: pyenvector
Requires-Dist: langchain>=0.2.0
